dbt_common/__about__.py
dbt_common/__init__.py
dbt_common/behavior_flags.py
dbt_common/constants.py
dbt_common/context.py
dbt_common/dataclass_schema.py
dbt_common/helper_types.py
dbt_common/invocation.py
dbt_common/py.typed
dbt_common/record.py
dbt_common/semver.py
dbt_common/tests.py
dbt_common/ui.py
dbt_common/clients/__init__.py
dbt_common/clients/_jinja_blocks.py
dbt_common/clients/agate_helper.py
dbt_common/clients/jinja.py
dbt_common/clients/system.py
dbt_common/contracts/__init__.py
dbt_common/contracts/constraints.py
dbt_common/contracts/metadata.py
dbt_common/contracts/util.py
dbt_common/contracts/config/__init__.py
dbt_common/contracts/config/base.py
dbt_common/contracts/config/materialization.py
dbt_common/contracts/config/metadata.py
dbt_common/contracts/config/properties.py
dbt_common/events/README.md
dbt_common/events/__init__.py
dbt_common/events/base_types.py
dbt_common/events/contextvars.py
dbt_common/events/event_handler.py
dbt_common/events/event_manager.py
dbt_common/events/event_manager_client.py
dbt_common/events/format.py
dbt_common/events/functions.py
dbt_common/events/helpers.py
dbt_common/events/interfaces.py
dbt_common/events/logger.py
dbt_common/events/types.py
dbt_common/events/types_pb2.py
dbt_common/exceptions/__init__.py
dbt_common/exceptions/base.py
dbt_common/exceptions/cache.py
dbt_common/exceptions/connection.py
dbt_common/exceptions/contracts.py
dbt_common/exceptions/events.py
dbt_common/exceptions/jinja.py
dbt_common/exceptions/macros.py
dbt_common/exceptions/system.py
dbt_common/utils/__init__.py
dbt_common/utils/casting.py
dbt_common/utils/connection.py
dbt_common/utils/dict.py
dbt_common/utils/encoding.py
dbt_common/utils/executor.py
dbt_common/utils/formatting.py
dbt_common/utils/jinja.py
dbt_common-2.0.0.dist-info/METADATA
dbt_common-2.0.0.dist-info/WHEEL
dbt_common-2.0.0.dist-info/licenses/LICENSE
dbt_common-2.0.0.dist-info/RECORD
