Metadata-Version: 2.4
Name: dbt-common
Version: 2.0.0
Summary: The shared common utilities that dbt-core and adapter implementations use
Project-URL: Homepage, https://github.com/dbt-labs/dbt-common
Project-URL: Repository, https://github.com/dbt-labs/dbt-common.git
Project-URL: Issues, https://github.com/dbt-labs/dbt-common/issues
Project-URL: Changelog, https://github.com/dbt-labs/dbt-common/blob/main/CHANGELOG.md
Author-email: dbt Labs <info@dbtlabs.com>
Maintainer-email: dbt Labs <info@dbtlabs.com>
License-Expression: Apache-2.0
License-File: LICENSE
Classifier: Development Status :: 2 - Pre-Alpha
Classifier: License :: OSI Approved :: Apache Software License
Classifier: Operating System :: MacOS :: MacOS X
Classifier: Operating System :: Microsoft :: Windows
Classifier: Operating System :: POSIX :: Linux
Classifier: Programming Language :: Python
Classifier: Programming Language :: Python :: 3.9
Classifier: Programming Language :: Python :: 3.10
Classifier: Programming Language :: Python :: 3.11
Classifier: Programming Language :: Python :: 3.12
Classifier: Programming Language :: Python :: 3.13
Classifier: Programming Language :: Python :: Implementation :: CPython
Classifier: Programming Language :: Python :: Implementation :: PyPy
Requires-Python: >=3.9
Requires-Dist: agate<1.10,>=1.7.0
Requires-Dist: colorama<0.5,>=0.3.9
Requires-Dist: dbt-protos<2.0.0,>=1.0.291
Requires-Dist: deepdiff<8.0,>=7.0
Requires-Dist: isodate<0.7,>=0.6
Requires-Dist: jinja2<4,>=3.1.3
Requires-Dist: jsonschema<5.0,>=4.0
Requires-Dist: mashumaro[msgpack]<4.0,>=3.9
Requires-Dist: pathspec<0.13,>=0.9
Requires-Dist: protobuf<6.0,>=5.0
Requires-Dist: python-dateutil<3.0,>=2.0
Requires-Dist: requests<3.0.0
Requires-Dist: typing-extensions<5.0,>=4.4
Provides-Extra: build
Requires-Dist: check-wheel-contents; extra == 'build'
Requires-Dist: twine; extra == 'build'
Requires-Dist: wheel; extra == 'build'
Provides-Extra: lint
Requires-Dist: black<24.0,>=23.3; extra == 'lint'
Requires-Dist: flake8; extra == 'lint'
Requires-Dist: flake8-docstrings; extra == 'lint'
Requires-Dist: flake8-pyproject; extra == 'lint'
Requires-Dist: mypy<2.0,>=1.3; extra == 'lint'
Requires-Dist: pytest<8.0,>=7.3; extra == 'lint'
Requires-Dist: types-jinja2<3.0,>=2.11; extra == 'lint'
Requires-Dist: types-jsonschema<5.0,>=4.17; extra == 'lint'
Requires-Dist: types-protobuf<6.0,>=5.0; extra == 'lint'
Requires-Dist: types-python-dateutil<3.0,>=2.8; extra == 'lint'
Requires-Dist: types-pyyaml<7.0,>=6.0; extra == 'lint'
Requires-Dist: types-requests; extra == 'lint'
Provides-Extra: test
Requires-Dist: hypothesis<7.0,>=6.87; extra == 'test'
Requires-Dist: pytest-cov<5.0,>=4.1; extra == 'test'
Requires-Dist: pytest-mock; extra == 'test'
Requires-Dist: pytest-xdist<4.0,>=3.2; extra == 'test'
Requires-Dist: pytest<8.0,>=7.3; extra == 'test'
